mlcf/__init__.py
mlcf/datatools/__init__.py
mlcf/datatools/data_intervals.py
mlcf/datatools/data_reader.py
mlcf/datatools/standardisation.py
mlcf/datatools/utils.py
mlcf/indicators/__init__.py
mlcf/indicators/_indicators_tools.py
mlcf/indicators/add_indicators.py
mlcf/indicators/indicators_fct/__init__.py
mlcf/indicators/indicators_fct/custom_indicators.py
mlcf/indicators/indicators_fct/statistical_indicators.py
mlcf/indicators/indicators_fct/ta_indicators.py
mlcf/windowing/__init__.py
mlcf/windowing/filtering/__init__.py
mlcf/windowing/filtering/filter.py
mlcf/windowing/filtering/label_balance_filter.py
mlcf/windowing/iterator/__init__.py
mlcf/windowing/iterator/forecast_iterator.py
mlcf/windowing/iterator/iterator.py
mlcf/windowing/iterator/tseries.py
mlcf/windowing/iterator/tseries_lite.py
mlcf-2.2.6.dist-info/LICENSE
mlcf-2.2.6.dist-info/METADATA
mlcf-2.2.6.dist-info/WHEEL
mlcf-2.2.6.dist-info/top_level.txt
mlcf-2.2.6.dist-info/RECORD
