Metadata-Version: 2.1
Name: mlcf
Version: 2.2.6
Summary: MLCF - Machine Learning Toolkit for Cryptocurrency Forecasting
Home-page: https://github.com/Guitheg/mlcf/tree/main
Author: Guitheg, Embraysite
Author-email: gthgobin@gmail.com, costes.ambroise@gmail.com
License: GPLv3
Keywords: finance,machine-learning,ai,deep-learning,time-series,toolkit,cryptocurrency,neural-networks,forecasting,trading-algorithm,investment,trading-agent,mlcf
Classifier: Development Status :: 2 - Pre-Alpha
Classifier: Environment :: Console
Classifier: Environment :: GPU :: NVIDIA CUDA :: 11.3
Classifier: License :: OSI Approved :: GNU General Public License v3 (GPLv3)
Classifier: Natural Language :: English
Classifier: Operating System :: POSIX
Classifier: Programming Language :: Python :: 3 :: Only
Classifier: Programming Language :: Python :: 3.7
Classifier: Programming Language :: Python :: 3.8
Classifier: Programming Language :: Python :: 3.9
Classifier: Topic :: Desktop Environment :: File Managers
Classifier: Topic :: Education
Classifier: Topic :: Office/Business :: Financial :: Investment
Classifier: Topic :: Scientific/Engineering :: Artificial Intelligence
Classifier: Intended Audience :: Science/Research
Classifier: Intended Audience :: Developers
Requires-Python: >=3.7
License-File: LICENSE
Requires-Dist: pandas-ta
Requires-Dist: tsfresh
Requires-Dist: sklearn
Requires-Dist: tables
Requires-Dist: TA-Lib
